{
  "variants": {
    "facing=north": {
      "model": "minecraft:block/chiseled_bookshelf"
    },
    "facing=south": {
      "model": "minecraft:block/chiseled_bookshelf",
      "y": 180
    },
    "facing=east": {
      "model": "minecraft:block/chiseled_bookshelf",
      "y": 90
    },
    "facing=west": {
      "model": "minecraft:block/chiseled_bookshelf",
      "y": 270
    }
  },
  "multipart": [
    {
      "when": { "book_type_0": "normal" },
      "apply": { "model": "minecraft:block/chiseled_bookshelf_occupied_slot_top_left" }
    },
    {
      "when": { "book_type_0": "enchanted" },
      "apply": { "model": "minecraft:block/chiseled_bookshelf_enchanted_slot_top_left" }
    },

    {
      "when": { "book_type_1": "normal" },
      "apply": { "model": "minecraft:block/chiseled_bookshelf_occupied_slot_top_mid" }
    },
    {
      "when": { "book_type_1": "enchanted" },
      "apply": { "model": "minecraft:block/chiseled_bookshelf_enchanted_slot_top_mid" }
    },

    {
      "when": { "book_type_2": "normal" },
      "apply": { "model": "minecraft:block/chiseled_bookshelf_occupied_slot_top_right" }
    },
    {
      "when": { "book_type_2": "enchanted" },
      "apply": { "model": "minecraft:block/chiseled_bookshelf_enchanted_slot_top_right" }
    },

    {
      "when": { "book_type_3": "normal" },
      "apply": { "model": "minecraft:block/chiseled_bookshelf_occupied_slot_bottom_left" }
    },
    {
      "when": { "book_type_3": "enchanted" },
      "apply": { "model": "minecraft:block/chiseled_bookshelf_enchanted_slot_bottom_left" }
    },

    {
      "when": { "book_type_4": "normal" },
      "apply": { "model": "minecraft:block/chiseled_bookshelf_occupied_slot_bottom_mid" }
    },
    {
      "when": { "book_type_4": "enchanted" },
      "apply": { "model": "minecraft:block/chiseled_bookshelf_enchanted_slot_bottom_mid" }
    },

    {
      "when": { "book_type_5": "normal" },
      "apply": { "model": "minecraft:block/chiseled_bookshelf_occupied_slot_bottom_right" }
    },
    {
      "when": { "book_type_5": "enchanted" },
      "apply": { "model": "minecraft:block/chiseled_bookshelf_enchanted_slot_bottom_right" }
    },
    {
      "when": { "book_type_0": "normal" },
      "apply": { "model": "minecraft:block/chiseled_bookshelf_occupied_slot_top_left" },
      "y": 180
    },
    {
      "when": { "book_type_0": "enchanted" },
      "apply": { "model": "minecraft:block/chiseled_bookshelf_enchanted_slot_top_left" },
      "y": 180
    },

    {
      "when": { "book_type_1": "normal" },
      "apply": { "model": "minecraft:block/chiseled_bookshelf_occupied_slot_top_mid" },
      "y": 180
    },
    {
      "when": { "book_type_1": "enchanted" },
      "apply": { "model": "minecraft:block/chiseled_bookshelf_enchanted_slot_top_mid" },
      "y": 180
    },

    {
      "when": { "book_type_2": "normal" },
      "apply": { "model": "minecraft:block/chiseled_bookshelf_occupied_slot_top_right" },
      "y": 180
    },
    {
      "when": { "book_type_2": "enchanted" },
      "apply": { "model": "minecraft:block/chiseled_bookshelf_enchanted_slot_top_right" },
      "y": 180
    },

    {
      "when": { "book_type_3": "normal" },
      "apply": { "model": "minecraft:block/chiseled_bookshelf_occupied_slot_bottom_left" },
      "y": 180
    },
    {
      "when": { "book_type_3": "enchanted" },
      "apply": { "model": "minecraft:block/chiseled_bookshelf_enchanted_slot_bottom_left" },
      "y": 180
    },

    {
      "when": { "book_type_4": "normal" },
      "apply": { "model": "minecraft:block/chiseled_bookshelf_occupied_slot_bottom_mid" },
      "y": 180
    },
    {
      "when": { "book_type_4": "enchanted" },
      "apply": { "model": "minecraft:block/chiseled_bookshelf_enchanted_slot_bottom_mid" },
      "y": 180
    },

    {
      "when": { "book_type_5": "normal" },
      "apply": { "model": "minecraft:block/chiseled_bookshelf_occupied_slot_bottom_right" },
      "y": 180
    },
    {
      "when": { "book_type_5": "enchanted" },
      "apply": { "model": "minecraft:block/chiseled_bookshelf_enchanted_slot_bottom_right" },
      "y": 180
    },
    {
      "when": { "book_type_0": "normal" },
      "apply": { "model": "minecraft:block/chiseled_bookshelf_occupied_slot_top_left" },
      "y": 90
    },
    {
      "when": { "book_type_0": "enchanted" },
      "apply": { "model": "minecraft:block/chiseled_bookshelf_enchanted_slot_top_left" },
      "y": 90
    },

    {
      "when": { "book_type_1": "normal" },
      "apply": { "model": "minecraft:block/chiseled_bookshelf_occupied_slot_top_mid" },
      "y": 90
    },
    {
      "when": { "book_type_1": "enchanted" },
      "apply": { "model": "minecraft:block/chiseled_bookshelf_enchanted_slot_top_mid" },
      "y": 90
    },

    {
      "when": { "book_type_2": "normal" },
      "apply": { "model": "minecraft:block/chiseled_bookshelf_occupied_slot_top_right" },
      "y": 90
    },
    {
      "when": { "book_type_2": "enchanted" },
      "apply": { "model": "minecraft:block/chiseled_bookshelf_enchanted_slot_top_right" },
      "y": 90
    },

    {
      "when": { "book_type_3": "normal" },
      "apply": { "model": "minecraft:block/chiseled_bookshelf_occupied_slot_bottom_left" },
      "y": 90
    },
    {
      "when": { "book_type_3": "enchanted" },
      "apply": { "model": "minecraft:block/chiseled_bookshelf_enchanted_slot_bottom_left" },
      "y": 90
    },

    {
      "when": { "book_type_4": "normal" },
      "apply": { "model": "minecraft:block/chiseled_bookshelf_occupied_slot_bottom_mid" },
      "y": 90
    },
    {
      "when": { "book_type_4": "enchanted" },
      "apply": { "model": "minecraft:block/chiseled_bookshelf_enchanted_slot_bottom_mid" },
      "y": 90
    },

    {
      "when": { "book_type_5": "normal" },
      "apply": { "model": "minecraft:block/chiseled_bookshelf_occupied_slot_bottom_right" },
      "y": 90
    },
    {
      "when": { "book_type_5": "enchanted" },
      "apply": { "model": "minecraft:block/chiseled_bookshelf_enchanted_slot_bottom_right" },
      "y": 90
    },
    {
      "when": { "book_type_0": "normal" },
      "apply": { "model": "minecraft:block/chiseled_bookshelf_occupied_slot_top_left" },
      "y": 270
    },
    {
      "when": { "book_type_0": "enchanted" },
      "apply": { "model": "minecraft:block/chiseled_bookshelf_enchanted_slot_top_left" },
      "y": 270
    },

    {
      "when": { "book_type_1": "normal" },
      "apply": { "model": "minecraft:block/chiseled_bookshelf_occupied_slot_top_mid" },
      "y": 270
    },
    {
      "when": { "book_type_1": "enchanted" },
      "apply": { "model": "minecraft:block/chiseled_bookshelf_enchanted_slot_top_mid" },
      "y": 270
    },

    {
      "when": { "book_type_2": "normal" },
      "apply": { "model": "minecraft:block/chiseled_bookshelf_occupied_slot_top_right" },
      "y": 270
    },
    {
      "when": { "book_type_2": "enchanted" },
      "apply": { "model": "minecraft:block/chiseled_bookshelf_enchanted_slot_top_right" },
      "y": 270
    },

    {
      "when": { "book_type_3": "normal" },
      "apply": { "model": "minecraft:block/chiseled_bookshelf_occupied_slot_bottom_left" },
      "y": 270
    },
    {
      "when": { "book_type_3": "enchanted" },
      "apply": { "model": "minecraft:block/chiseled_bookshelf_enchanted_slot_bottom_left" },
      "y": 270
    },

    {
      "when": { "book_type_4": "normal" },
      "apply": { "model": "minecraft:block/chiseled_bookshelf_occupied_slot_bottom_mid" },
      "y": 270
    },
    {
      "when": { "book_type_4": "enchanted" },
      "apply": { "model": "minecraft:block/chiseled_bookshelf_enchanted_slot_bottom_mid" },
      "y": 270
    },

    {
      "when": { "book_type_5": "normal" },
      "apply": { "model": "minecraft:block/chiseled_bookshelf_occupied_slot_bottom_right" },
      "y": 270
    },
    {
      "when": { "book_type_5": "enchanted" },
      "apply": { "model": "minecraft:block/chiseled_bookshelf_enchanted_slot_bottom_right" },
      "y": 270
    }
  ]
}
